xssecure/__init__.py
xssecure/sanitize.py
xssecure/whitelist_attributes.txt
xssecure/whitelist_tags.txt
xssecure-0.0.5.dist-info/LICENSE
xssecure-0.0.5.dist-info/METADATA
xssecure-0.0.5.dist-info/WHEEL
xssecure-0.0.5.dist-info/top_level.txt
xssecure-0.0.5.dist-info/RECORD
